[
  {
    "description": "Use the back-end API firewall, then you can transmit the cross-platform card!",
    "developers": ["Rebecca Tromp", "Tiffany Lehner", "Herman Simonis"],
    "repository": "strict-gastropod"
  },
  {
    "description": "We need to calculate the virtual JSON transmitter!",
    "developers": [
      "Elvira Lang",
      "Ernesto Ernser",
      "Marilyn Gulgowski",
      "Diane Kutch",
      "Mae Schneider I"
    ],
    "repository": "outlying-antelope"
  },
  {
    "description": "If we quantify the capacitor, we can get to the SMS bandwidth through the haptic CSS hard drive!",
    "developers": ["Beth Schneider", "Terrance Franey", "Sean Dicki"],
    "repository": "deficient-retention"
  },
  {
    "description": "Indexing the monitor won't do anything, we need to synthesize the digital THX driver!",
    "developers": [
      "Felix Ward",
      "Dr. Geraldine Schneider",
      "Paula Christiansen",
      "Edmund Bernhard",
      "Martha Koss"
    ],
    "repository": "strident-detective"
  },
  {
    "description": "You can't bypass the sensor without copying the neural COM panel!",
    "developers": ["Jenny Effertz", "Nina Quigley", "Mr. Taylor Treutel"],
    "repository": "made-up-hamburger"
  },
  {
    "description": "Try to calculate the USB circuit, maybe it will copy the haptic interface!",
    "developers": [
      "Martin Kulas",
      "Miss Bernice Fritsch DVM",
      "Nick Hagenes",
      "Christine Metz"
    ],
    "repository": "short-term-piglet"
  },
  {
    "description": "Copying the program won't do anything, we need to program the open-source ADP firewall!",
    "developers": [
      "Darnell Hermiston",
      "Irma Blick",
      "Steven Collier",
      "Geraldine Green",
      "Bradford Stroman"
    ],
    "repository": "fuzzy-premise"
  },
  {
    "description": "Use the digital API matrix, then you can generate the solid state interface!",
    "developers": [
      "Jody Boehm",
      "Merle Dibbert",
      "Edwin Rice DDS",
      "Kay Veum",
      "Mack Murphy"
    ],
    "repository": "early-designation"
  },
  {
    "description": "I'll index the bluetooth JBOD hard drive, that should application the HEX driver!",
    "developers": [
      "Gina Jacobs",
      "Maxine Strosin PhD",
      "Bessie Collins",
      "Lorenzo Renner"
    ],
    "repository": "nocturnal-chap"
  },
  {
    "description": "Hacking the alarm won't do anything, we need to parse the haptic AI transmitter!",
    "developers": [
      "Rafael McGlynn",
      "Enrique Kulas",
      "Mr. Tommy Barrows Jr.",
      "Terry Witting",
      "Clyde Schamberger"
    ],
    "repository": "ambitious-mousse"
  },
  {
    "description": "You can't navigate the port without hacking the haptic JBOD monitor!",
    "developers": [
      "Bernadette Corwin III",
      "Scott Schowalter-Crona",
      "Shelley Durgan Jr.",
      "Miranda Little",
      "Vivian Little"
    ],
    "repository": "rich-overcoat"
  },
  {
    "description": "The TCP card is down, back up the cross-platform program so we can generate the TCP alarm!",
    "developers": [
      "Emanuel Rath",
      "Keith Schowalter",
      "Dr. Darren Beahan",
      "Darlene Lueilwitz",
      "Edna Klein III"
    ],
    "repository": "aggressive-cash"
  },
  {
    "description": "Try to back up the ADP monitor, maybe it will back up the redundant microchip!",
    "developers": ["Pam Weimann III", "Ernest Ortiz", "Randy Labadie-Mohr"],
    "repository": "pertinent-newsstand"
  },
  {
    "description": "If we connect the program, we can get to the UDP alarm through the primary JSON hard drive!",
    "developers": ["Jose Kemmer MD", "Lula Flatley-King", "Jenna Kirlin"],
    "repository": "untrue-hospitalization"
  },
  {
    "description": "We need to parse the solid state RAM protocol!",
    "developers": ["Marlon Schowalter", "Caroline Waelchi", "Mary Douglas"],
    "repository": "crushing-duffel"
  },
  {
    "description": "The API array is down, input the virtual transmitter so we can program the UTF8 firewall!",
    "developers": ["Dr. Bridget Shields", "Shane Tromp", "Tom Franey"],
    "repository": "mammoth-secrecy"
  },
  {
    "description": "The TLS hard drive is down, calculate the multi-byte hard drive so we can compress the SQL capacitor!",
    "developers": ["Jan Purdy", "Mae Padberg Jr.", "Valerie Roberts"],
    "repository": "best-acquaintance"
  },
  {
    "description": "If we back up the bus, we can get to the FTP driver through the haptic SSD microchip!",
    "developers": ["Hugh Roob", "Rochelle Nolan", "Hope Purdy DDS"],
    "repository": "alive-presume"
  },
  {
    "description": "Use the solid state AI microchip, then you can reboot the cross-platform sensor!",
    "developers": [
      "Stephanie Macejkovic",
      "Marcia Langworth",
      "Mary Haley",
      "Antonia Senger"
    ],
    "repository": "lonely-brush"
  },
  {
    "description": "Try to quantify the HDD bus, maybe it will input the digital monitor!",
    "developers": [
      "Marshall Lynch",
      "Mrs. Julie Williamson",
      "Kate Dickinson",
      "Mrs. Kari Weber",
      "June Welch"
    ],
    "repository": "miserable-minority"
  },
  {
    "description": "Use the redundant SSD array, then you can program the solid state matrix!",
    "developers": [
      "Jacob Kautzer",
      "Earl Von",
      "Tyrone Volkman",
      "Alfred Mosciski"
    ],
    "repository": "fruitful-schedule"
  },
  {
    "description": "You can't copy the program without synthesizing the optical THX bandwidth!",
    "developers": ["Gladys Weber-Feeney", "Dr. Caleb Tremblay", "Phil Kemmer"],
    "repository": "edible-blowgun"
  },
  {
    "description": "You can't compress the hard drive without transmitting the 1080p SSL card!",
    "developers": [
      "Alan Ortiz",
      "Marguerite Effertz-Lockman",
      "Ernestine Lesch",
      "Dustin Wilderman-Hermiston"
    ],
    "repository": "hollow-fork"
  },
  {
    "description": "Use the optical IB card, then you can parse the auxiliary pixel!",
    "developers": ["Pat Buckridge", "Mrs. Kathryn Hammes", "Carlton Mayer"],
    "repository": "glass-word"
  },
  {
    "description": "You can't hack the system without programming the multi-byte JSON port!",
    "developers": ["Terry Ondricka", "Miss Leona Dare", "Anita Moore"],
    "repository": "yummy-negotiation"
  },
  {
    "description": "I'll transmit the redundant XML bandwidth, that should feed the USB feed!",
    "developers": [
      "Della Fisher-Metz",
      "Mr. Clarence Pouros",
      "Olive Waelchi DVM",
      "Katherine Windler"
    ],
    "repository": "breakable-signature"
  },
  {
    "description": "If we index the panel, we can get to the SDD transmitter through the neural ASCII program!",
    "developers": [
      "Johanna Keeling",
      "Jodi Treutel",
      "Tyrone Corkery",
      "Dorothy Roberts",
      "Ms. Sherri Feest DVM"
    ],
    "repository": "self-assured-advertisement"
  },
  {
    "description": "You can't program the panel without parsing the mobile SDD pixel!",
    "developers": [
      "Dr. Alvin Rogahn",
      "Willie Prosacco",
      "Mrs. Juanita Ebert",
      "Alan VonRueden",
      "Trevor Jakubowski-Sporer"
    ],
    "repository": "knowledgeable-reboot"
  },
  {
    "description": "You can't parse the port without compressing the bluetooth AI sensor!",
    "developers": [
      "Roland Wuckert",
      "Dianna Kshlerin",
      "Shawna Williamson",
      "Cameron Davis",
      "Lillian Towne-Wilkinson PhD"
    ],
    "repository": "glossy-handful"
  },
  {
    "description": "Connecting the card won't do anything, we need to quantify the primary IP capacitor!",
    "developers": [
      "Desiree Hayes Jr.",
      "Amber Greenholt",
      "Lester Shields PhD"
    ],
    "repository": "parallel-fisherman"
  },
  {
    "description": "I'll connect the virtual SSD alarm, that should matrix the OCR array!",
    "developers": [
      "Tommie Purdy",
      "Beverly Tillman",
      "Aaron McLaughlin Sr.",
      "Melanie Krajcik",
      "Chad Kuhn Sr."
    ],
    "repository": "forceful-finer"
  },
  {
    "description": "You can't input the driver without indexing the virtual SMTP firewall!",
    "developers": [
      "Darrel Kerluke",
      "Edwin Schumm",
      "Belinda Farrell",
      "Claudia Bruen-Bernhard DDS",
      "Erika Kassulke"
    ],
    "repository": "expert-corral"
  },
  {
    "description": "The JBOD protocol is down, generate the auxiliary application so we can calculate the SDD array!",
    "developers": [
      "Mr. Daryl Mann",
      "Betsy Hettinger",
      "Inez Rippin Jr.",
      "Angelica Stark",
      "Percy Stehr"
    ],
    "repository": "impressionable-best-seller"
  },
  {
    "description": "We need to parse the wireless HDD array!",
    "developers": [
      "Alfred Smith",
      "Arnold Auer DVM",
      "Perry Abshire",
      "Julian Wilderman"
    ],
    "repository": "cheap-petticoat"
  },
  {
    "description": "Quantifying the interface won't do anything, we need to calculate the bluetooth USB port!",
    "developers": [
      "Gladys Adams",
      "Lola Pfannerstill",
      "Mr. Andrew Bins",
      "Willard Volkman Jr."
    ],
    "repository": "odd-cinema"
  },
  {
    "description": "Use the neural SMS protocol, then you can input the bluetooth feed!",
    "developers": ["Joe Berge", "Mildred Swift III", "Henrietta Hessel"],
    "repository": "jealous-middle"
  },
  {
    "description": "I'll index the digital VGA interface, that should system the PNG microchip!",
    "developers": [
      "Angie Heaney",
      "Dr. Kay Renner",
      "Kendra Hermiston",
      "Pam Keeling"
    ],
    "repository": "lonely-hydrocarbon"
  },
  {
    "description": "I'll copy the solid state ADP bandwidth, that should alarm the ADP bus!",
    "developers": ["Darnell Fadel", "Nichole Veum", "Wilbert McClure"],
    "repository": "rosy-laughter"
  },
  {
    "description": "The DRAM microchip is down, generate the digital system so we can back up the DNS alarm!",
    "developers": ["Lillie Rosenbaum", "Dr. Cynthia Olson", "Jorge Jerde"],
    "repository": "well-documented-recommendation"
  },
  {
    "description": "If we program the matrix, we can get to the XML application through the multi-byte AI array!",
    "developers": [
      "Dr. Flora Dickinson MD",
      "Carrie Mayert",
      "Colleen Schuster II"
    ],
    "repository": "tinted-veto"
  },
  {
    "description": "If we generate the capacitor, we can get to the SSD feed through the online OCR program!",
    "developers": [
      "Trevor Pfannerstill",
      "Miss Ana Brown",
      "Joyce Cummerata PhD"
    ],
    "repository": "vengeful-grandson"
  },
  {
    "description": "If we connect the system, we can get to the TCP application through the bluetooth IB driver!",
    "developers": ["Cory Dooley", "Dr. Myron Johnston", "Katrina Bauch"],
    "repository": "confused-challenge"
  },
  {
    "description": "Use the cross-platform SMS bus, then you can input the wireless hard drive!",
    "developers": ["Kristopher Stark", "Adrienne Von", "Delbert Gleichner"],
    "repository": "pure-granny"
  },
  {
    "description": "The TLS firewall is down, reboot the online capacitor so we can generate the HEX port!",
    "developers": [
      "Florence Hickle",
      "Al Nader",
      "Dr. Elbert Watsica",
      "Stacey Schuppe"
    ],
    "repository": "austere-poppy"
  },
  {
    "description": "The SAS circuit is down, hack the digital pixel so we can compress the CSS monitor!",
    "developers": [
      "Elsa Heaney",
      "Marjorie Adams",
      "Rita Daniel",
      "Yvette Breitenberg"
    ],
    "repository": "trivial-tennis"
  },
  {
    "description": "The TLS firewall is down, override the online circuit so we can program the SDD card!",
    "developers": ["Karen Anderson-Welch", "Mr. Jose Kuphal", "Bill Miller"],
    "repository": "writhing-ghost"
  },
  {
    "description": "Try to back up the EXE panel, maybe it will input the open-source alarm!",
    "developers": ["Fredrick Koch", "Patty Mann", "Grady Mayert"],
    "repository": "easy-barracks"
  },
  {
    "description": "If we navigate the alarm, we can get to the PCI array through the wireless TCP array!",
    "developers": [
      "Sherri Halvorson",
      "Terence Kiehn",
      "Mrs. Mandy Kozey",
      "Allen Leffler",
      "Brent Bailey"
    ],
    "repository": "alarmed-sailor"
  },
  {
    "description": "Use the optical JBOD port, then you can transmit the solid state interface!",
    "developers": ["Alejandro Dickinson", "Milton Trantow", "Benny Franey"],
    "repository": "gorgeous-parsnip"
  },
  {
    "description": "The PNG bus is down, transmit the optical capacitor so we can quantify the OCR system!",
    "developers": ["Eloise Swaniawski", "Gail Ledner", "Iris Strosin"],
    "repository": "clueless-accompanist"
  },
  {
    "description": "Use the back-end UTF8 hard drive, then you can input the redundant bus!",
    "developers": [
      "Christine Mills-Nolan",
      "Jane Torp-Stroman",
      "Christie Emard",
      "Marcella Yundt",
      "Rodolfo Lindgren"
    ],
    "repository": "strident-pillow"
  },
  {
    "description": "Use the online IB capacitor, then you can navigate the haptic sensor!",
    "developers": [
      "Luz D'Amore",
      "Lois Wehner",
      "Carrie Bernier",
      "Marc Thiel",
      "Muriel Franey"
    ],
    "repository": "webbed-marketplace"
  },
  {
    "description": "The JSON pixel is down, hack the multi-byte bandwidth so we can back up the TLS transmitter!",
    "developers": ["Joseph Hills", "Brittany Nienow", "Orville Lakin III"],
    "repository": "limited-address"
  },
  {
    "description": "Use the online HTTP feed, then you can parse the wireless panel!",
    "developers": [
      "Candace Weber",
      "Felipe Schulist",
      "Mrs. Marlene Veum",
      "Joey Kozey",
      "Katherine Hermiston"
    ],
    "repository": "stylish-middle"
  },
  {
    "description": "Connecting the array won't do anything, we need to back up the optical SCSI monitor!",
    "developers": ["Jose Thiel", "Cristina Effertz", "Cynthia Dibbert"],
    "repository": "chubby-climb"
  },
  {
    "description": "Use the back-end SDD microchip, then you can synthesize the virtual sensor!",
    "developers": [
      "Phyllis Dietrich",
      "Alicia Braun",
      "Barbara Williamson",
      "Robyn Schmidt",
      "Connie Johnson"
    ],
    "repository": "agreeable-retention"
  },
  {
    "description": "If we index the firewall, we can get to the SQL interface through the redundant SSD application!",
    "developers": [
      "Dr. Dwayne Cartwright",
      "Tasha Hickle",
      "Tomas Rowe",
      "Minnie Toy DVM",
      "Preston Borer"
    ],
    "repository": "immediate-calculus"
  },
  {
    "description": "Use the haptic SMS application, then you can quantify the 1080p application!",
    "developers": ["Christina Wuckert", "Cecelia Volkman", "Jorge Konopelski"],
    "repository": "intent-stump"
  },
  {
    "description": "Use the haptic RSS array, then you can compress the 1080p bus!",
    "developers": [
      "Mercedes Ernser",
      "Jeanne Hansen",
      "Lynn Wilkinson",
      "Elvira Conroy"
    ],
    "repository": "every-academics"
  },
  {
    "description": "If we compress the microchip, we can get to the UDP driver through the solid state XSS protocol!",
    "developers": ["Denise Adams", "Jacqueline Walsh", "Nathaniel Feest"],
    "repository": "functional-costume"
  },
  {
    "description": "I'll input the online RAM protocol, that should port the ASCII alarm!",
    "developers": ["Sabrina Stiedemann", "Lisa Halvorson", "Ms. Eileen Adams"],
    "repository": "devoted-gastropod"
  },
  {
    "description": "Try to generate the OCR driver, maybe it will transmit the open-source alarm!",
    "developers": ["Jorge Maggio", "Courtney Little", "Erin Volkman"],
    "repository": "simplistic-ad"
  },
  {
    "description": "You can't parse the panel without connecting the haptic THX capacitor!",
    "developers": [
      "Orlando Grady",
      "Miss Lorena Price",
      "Miss Charlene Daugherty MD",
      "Kelly Pacocha"
    ],
    "repository": "small-harp"
  },
  {
    "description": "The JSON panel is down, generate the digital monitor so we can bypass the DNS feed!",
    "developers": ["Kurt Bogan", "Ann Kuhlman", "Flora Hagenes"],
    "repository": "silver-cow"
  },
  {
    "description": "If we compress the matrix, we can get to the TLS feed through the mobile ADP protocol!",
    "developers": ["Dr. Angel Hudson", "Mona Wolff", "Shawn Schneider III"],
    "repository": "hidden-cinder"
  },
  {
    "description": "We need to program the primary TCP circuit!",
    "developers": [
      "Adam Wisoky",
      "Virgil Sporer",
      "Jesse Herzog",
      "Clark Bergnaum"
    ],
    "repository": "rosy-information"
  },
  {
    "description": "The PCI firewall is down, compress the optical protocol so we can connect the IP microchip!",
    "developers": ["Nicholas Cormier Jr.", "Sherri Moore", "Cora Fahey"],
    "repository": "close-populist"
  },
  {
    "description": "Use the primary RSS circuit, then you can program the wireless protocol!",
    "developers": [
      "Camille Ritchie",
      "Gustavo Monahan",
      "Jessie Deckow",
      "Noah Weissnat"
    ],
    "repository": "beloved-riser"
  },
  {
    "description": "If we override the feed, we can get to the IP sensor through the redundant RAM feed!",
    "developers": [
      "Cheryl Erdman",
      "Jackie Schaden",
      "Dr. Johanna Zulauf-Hamill"
    ],
    "repository": "awesome-heating"
  },
  {
    "description": "The JSON driver is down, reboot the bluetooth transmitter so we can calculate the COM protocol!",
    "developers": [
      "Dr. Jacqueline Greenholt",
      "Danny Schinner",
      "Gene Macejkovic",
      "Monique Abbott",
      "Jake Swift"
    ],
    "repository": "odd-chainstay"
  },
  {
    "description": "The VGA bus is down, compress the redundant monitor so we can override the HDD panel!",
    "developers": [
      "Andre Gislason",
      "Guadalupe Osinski",
      "James Lueilwitz",
      "Sherman Ziemann",
      "Jeremy Gerlach"
    ],
    "repository": "enchanted-moment"
  },
  {
    "description": "Try to connect the PCI sensor, maybe it will reboot the redundant microchip!",
    "developers": ["Ann Moen", "Christy Ebert", "Marlene McGlynn"],
    "repository": "rapid-disk"
  },
  {
    "description": "Use the online AI array, then you can calculate the multi-byte protocol!",
    "developers": [
      "Philip Boyle",
      "Guadalupe Reynolds PhD",
      "Mamie Heathcote DVM",
      "Joanne Johnston",
      "Denise Morissette"
    ],
    "repository": "questionable-barge"
  },
  {
    "description": "If we back up the sensor, we can get to the SDD sensor through the neural CLI panel!",
    "developers": [
      "Jerald Hilll-Reichert V",
      "Chris Sawayn MD",
      "Dr. Clark Stehr MD"
    ],
    "repository": "prestigious-priesthood"
  },
  {
    "description": "Parsing the pixel won't do anything, we need to bypass the online TLS program!",
    "developers": ["Cristina Jast", "Jeremiah Runolfsson", "Rita Towne"],
    "repository": "miserly-chops"
  },
  {
    "description": "Navigating the driver won't do anything, we need to navigate the auxiliary TCP matrix!",
    "developers": [
      "Traci Schmidt",
      "Bill Bechtelar",
      "Muriel Wilderman",
      "Bob Orn",
      "Gloria Russel"
    ],
    "repository": "sure-footed-councilman"
  },
  {
    "description": "We need to hack the virtual AGP bus!",
    "developers": ["Natasha Leannon", "Maria Lynch", "Vivian Hirthe"],
    "repository": "free-singing"
  },
  {
    "description": "The HTTP array is down, connect the mobile pixel so we can compress the UTF8 interface!",
    "developers": [
      "Mr. Leo Orn V",
      "Julia Gusikowski",
      "Jeremy Bruen",
      "Teresa Stehr",
      "Frank Champlin"
    ],
    "repository": "unsightly-sweatshop"
  },
  {
    "description": "Quantifying the card won't do anything, we need to input the cross-platform XSS application!",
    "developers": [
      "Ed Runolfsson",
      "Archie Hane I",
      "Rogelio DuBuque",
      "Terry Cremin"
    ],
    "repository": "quick-witted-awareness"
  },
  {
    "description": "Overriding the pixel won't do anything, we need to input the redundant SQL sensor!",
    "developers": [
      "Miss Ana Padberg",
      "Vicky Leuschke",
      "Lois Armstrong",
      "Olive Lesch"
    ],
    "repository": "black-replacement"
  },
  {
    "description": "If we synthesize the matrix, we can get to the RAM transmitter through the wireless CLI program!",
    "developers": ["Anthony Wilkinson", "Courtney Kunde", "Wallace Quitzon"],
    "repository": "jittery-stock"
  },
  {
    "description": "Try to connect the RAM hard drive, maybe it will index the 1080p bus!",
    "developers": [
      "Ramon DuBuque",
      "Byron Ullrich Sr.",
      "Colin Gorczany DVM",
      "Miss Christy Gulgowski"
    ],
    "repository": "subtle-advancement"
  },
  {
    "description": "Try to input the SSD microchip, maybe it will override the bluetooth panel!",
    "developers": [
      "Marilyn McDermott PhD",
      "Billy Kub",
      "Rodolfo Kub",
      "Mabel Schinner"
    ],
    "repository": "glorious-statue"
  },
  {
    "description": "Try to generate the SSL system, maybe it will synthesize the bluetooth array!",
    "developers": [
      "Archie Quitzon",
      "Monique Larkin",
      "Cecelia Stokes I",
      "Karla Sanford",
      "Kendra Berge"
    ],
    "repository": "soft-drug"
  },
  {
    "description": "The IP pixel is down, back up the redundant bus so we can generate the CLI interface!",
    "developers": ["Julius Rath", "Michelle Kutch", "Debra Windler"],
    "repository": "free-halt"
  },
  {
    "description": "We need to input the back-end DRAM driver!",
    "developers": [
      "Edmund Klocko",
      "Marco Lynch",
      "Theodore Morar",
      "Rogelio Torp-Bosco II"
    ],
    "repository": "abandoned-language"
  },
  {
    "description": "Use the wireless DNS port, then you can calculate the optical interface!",
    "developers": [
      "Bernice Lang",
      "Roxanne Maggio",
      "Mr. Jermaine Bergstrom",
      "Henry Bernhard PhD",
      "Gail Schimmel"
    ],
    "repository": "scary-making"
  },
  {
    "description": "Use the redundant AI feed, then you can generate the wireless pixel!",
    "developers": [
      "Kristie Block MD",
      "Jeffrey Cormier-Erdman",
      "Ebony Pfannerstill",
      "Mrs. Stephanie Feeney"
    ],
    "repository": "tidy-signature"
  },
  {
    "description": "Try to bypass the HDD matrix, maybe it will generate the redundant program!",
    "developers": [
      "Shannon Metz",
      "Cornelius Simonis-Grimes",
      "Gertrude Kohler",
      "Ruth Hauck",
      "Trevor Bechtelar"
    ],
    "repository": "lost-instruction"
  },
  {
    "description": "Use the virtual FTP capacitor, then you can program the multi-byte card!",
    "developers": [
      "Doreen Berge",
      "Tony Senger",
      "Laurence Johnson",
      "Rochelle Dooley",
      "Milton Fay-Hammes"
    ],
    "repository": "friendly-step-mother"
  },
  {
    "description": "Connecting the program won't do anything, we need to connect the virtual UTF8 hard drive!",
    "developers": [
      "Faith Haag",
      "Lorenzo Schoen",
      "Blanca Monahan",
      "Austin Mitchell"
    ],
    "repository": "lined-mainstream"
  },
  {
    "description": "Copying the system won't do anything, we need to input the auxiliary SDD matrix!",
    "developers": ["Mrs. Victoria Donnelly", "Deborah Fahey", "Jimmy Fay"],
    "repository": "hot-safe"
  },
  {
    "description": "We need to override the wireless XSS circuit!",
    "developers": [
      "Dr. Marcos Christiansen",
      "Sonya Lynch",
      "Jaime Bins",
      "Mandy Williamson",
      "Robin Bernhard"
    ],
    "repository": "gentle-knuckle"
  },
  {
    "description": "We need to override the solid state THX monitor!",
    "developers": [
      "Harold Dach V",
      "Pablo Walsh",
      "Geraldine Moen",
      "Wanda Heathcote"
    ],
    "repository": "aged-horst"
  },
  {
    "description": "Try to connect the AI matrix, maybe it will hack the haptic circuit!",
    "developers": [
      "Dean Schinner",
      "Gene Nolan Sr.",
      "Mrs. Laurie Kihn",
      "Mrs. Samantha Dare II",
      "Adrienne Ortiz"
    ],
    "repository": "spotless-pliers"
  },
  {
    "description": "Try to index the DRAM bandwidth, maybe it will parse the cross-platform system!",
    "developers": ["Gretchen Wyman", "Drew Ziemann", "Shane Heller I"],
    "repository": "competent-alb"
  },
  {
    "description": "The PNG firewall is down, reboot the open-source microchip so we can index the HEX driver!",
    "developers": [
      "Edna Hettinger",
      "Louise Veum-Schulist",
      "Amelia Stark",
      "Jana Jerde"
    ],
    "repository": "gray-haircut"
  },
  {
    "description": "You can't index the alarm without hacking the redundant UTF8 card!",
    "developers": [
      "Kelley Hills",
      "Nicolas Rath",
      "Christine Johnston Sr.",
      "Beth Larson"
    ],
    "repository": "actual-behest"
  },
  {
    "description": "If we program the transmitter, we can get to the IB alarm through the virtual PNG port!",
    "developers": ["Corey Blanda", "Mack Daniel", "Derrick Franecki Sr."],
    "repository": "unhealthy-pigpen"
  },
  {
    "description": "I'll bypass the virtual ASCII feed, that should program the SSL feed!",
    "developers": [
      "Mrs. Mattie Mueller-Borer I",
      "Freddie Brown",
      "Neal Powlowski",
      "Shawn Swift",
      "Stephanie VonRueden"
    ],
    "repository": "frail-heartache"
  }
]
